{
    "total": 11,
    "results": [
        {
            "id": 1,
            "date": "2021-02-05",
            "name": "Sophie Catherine",
            "email": "sohpie123@gmail.com",
            "phone": "987654321",
            "status": "Sample Not Submitted",
            "statusId": 1,
            "trainingAudioNumber": 0,
            "trainingDays": null,
            "trainingAverageScore": 0,
            "langauageName": "English",
            "languageId": 7
        },
        {
            "id": 2,
            "date": "2021-02-04",
            "name": "John Carter",
            "email": "john@gmail.com",
            "phone": null,
            "status": "Send for Rework",
            "statusId": 2,
            "trainingAudioNumber": 0,
            "trainingDays": null,
            "trainingAverageScore": 0,
            "langauageName": "English",
            "languageId": 7
        },
        {
            "id": 3,
            "date": "2021-02-04",
            "name": "Marie Jane",
            "email": "marie@gmail.com",
            "phone": null,
            "status": "Sample Not Submitted",
            "statusId": 1,
            "trainingAudioNumber": 1,
            "trainingDays": 1,
            "trainingAverageScore": 0,
            "langauageName": "Malyali",
            "languageId": 6
        },
        {
            "id": 4,
            "date": "2021-02-03",
            "name": "Hugh Jackman",
            "email": "wolverine@gmail.com",
            "phone": null,
            "status": "Sample Not Submitted",
            "statusId": 1,
            "trainingAudioNumber": 0,
            "trainingDays": null,
            "trainingAverageScore": 0,
            "langauageName": "Hindi",
            "languageId": 1
        },
        {
            "id": 5,
            "date": "2021-02-02",
            "name": "KP Oli",
            "email": "OliBaa@gmail.com",
            "phone": "9844012121",
            "status": "Send for Rework",
            "statusId": 2,
            "trainingAudioNumber": 0,
            "trainingDays": 47,
            "trainingAverageScore": 0,
            "langauageName": "Bengali",
            "languageId": 4
        },
        {
            "id": 6,
            "date": "2021-02-01",
            "name": "Bella Porsche",
            "email": "bella028@gmail.com",
            "phone": null,
            "status": "Cancelled",
            "statusId": 3,
            "trainingAudioNumber": 0,
            "trainingDays": null,
            "trainingAverageScore": 0,
            "langauageName": "Nepali",
            "languageId": 2
        },
        {
            "id": 7,
            "date": "2021-02-06",
            "name": "Lova Norman",
            "email": "lova.norman@gmail.com",
            "phone": null,
            "status": "Cancelled",
            "statusId": 3,
            "trainingAudioNumber": 1,
            "trainingDays": 1,
            "trainingAverageScore": 0,
            "langauageName": "Nepali",
            "languageId": 2
        },
        {
            "id": 8,
            "date": "2021-02-07",
            "name": "Apurba Kalai",
            "email": "kapurba@gmail.com",
            "phone": "(91)9880145697",
            "status": "Send for Rework",
            "statusId": 2,
            "trainingAudioNumber": 0,
            "trainingDays": 2,
            "trainingAverageScore": 0,
            "langauageName": "Hindi",
            "languageId": 1
        },
        {
            "id": 9,
            "date": "2021-01-28",
            "name": "Carmina Roe Amil",
            "email": "amil.roe@gmail.com",
            "phone": "(44)",
            "status": "Sample Not Submitted",
            "statusId": 1,
            "trainingAudioNumber": 1,
            "trainingDays": 1,
            "trainingAverageScore": 0,
            "langauageName": "Cantonese",
            "languageId": 3
        },
        {
            "id": 10,
            "date": "2021-01-30",
            "name": "Susan Chettri",
            "email": "chettri.susan@gmail.com",
            "phone": null,
            "status": "Cancelled",
            "statusId": 3,
            "trainingAudioNumber": 0,
            "trainingDays": null,
            "trainingAverageScore": 0,
            "langauageName": "Nepali",
            "languageId": 2
        },
        {
            "id": 11,
            "date": "2021-01-30",
            "name": "Melissa Valfes",
            "email": "melissa@gmail.com",
            "phone": null,
            "status": "Send for Rework",
            "statusId": 2,
            "trainingAudioNumber": 0,
            "trainingDays": 2,
            "trainingAverageScore": 0,
            "langauageName": "Tamil",
            "languageId": 5
        }
    ]
}